LICENSE.md
MANIFEST.in
README.rst
VERSION
setup.py
flowdas/__init__.py
flowdas/meter/__init__.py
flowdas/meter/engine.c
flowdas/meter/engine.h
flowdas/meter/event_epoll.c
flowdas/meter/event_kqueue.c
flowdas/meter/main.py
flowdas/meter/version.py
flowdas_meter.egg-info/PKG-INFO
flowdas_meter.egg-info/SOURCES.txt
flowdas_meter.egg-info/dependency_links.txt
flowdas_meter.egg-info/entry_points.txt
flowdas_meter.egg-info/namespace_packages.txt
flowdas_meter.egg-info/not-zip-safe
flowdas_meter.egg-info/requires.txt
flowdas_meter.egg-info/top_level.txt
vendor/http-parser/LICENSE-MIT
vendor/http-parser/README.md
vendor/http-parser/bench.c
vendor/http-parser/http_parser.c
vendor/http-parser/http_parser.h
vendor/http-parser/test.c
vendor/http-parser/contrib/parsertrace.c
vendor/http-parser/contrib/url_parser.c