Metadata-Version: 1.1
Name: flowdas-meter
Version: 0.2.0
Summary: Meter: A HTTP load generator
Home-page: https://bitbucket.org/flowdas/meter
Author: Flowdas Inc.
Author-email: prospero@flowdas.com
License: AGPL 3.0
Keywords: http,test,performance
Platform: UNKNOWN
Classifier: Development Status :: 5 - Production/Stable
Classifier: Intended Audience :: Developers
Classifier: Topic :: Software Development :: Libraries :: Python Modules
Classifier: License :: OSI Approved :: GNU Affero General Public License v3
Classifier: Operating System :: MacOS :: MacOS X
Classifier: Programming Language :: Python :: 3
Classifier: Programming Language :: Python :: 3.5
Classifier: Topic :: Internet
Classifier: Topic :: Utilities
Classifier: Topic :: Software Development :: Libraries :: Python Modules
Classifier: Topic :: Internet :: WWW/HTTP
